Metadata-Version: 2.1
Name: retro-palettes
Version: 3.0
Summary: Custom Palette For Visualization
Author-email: Habu <lksai.kanesa2023@gmail.com>
Classifier: Programming Language :: Python :: 3
Classifier: License :: OSI Approved :: MIT License
Classifier: Operating System :: OS Independent
Requires-Python: >=3.7
License-File: LICENSE
